wtf_cmd/__init__.py
wtf_cmd/cmd.py
wtf_cmd-0.2.1.dist-info/METADATA
wtf_cmd-0.2.1.dist-info/WHEEL
wtf_cmd-0.2.1.dist-info/entry_points.txt
wtf_cmd-0.2.1.dist-info/top_level.txt
wtf_cmd-0.2.1.dist-info/RECORD
