Metadata-Version: 2.1
Name: wtf_cmd
Version: 0.2.1
Summary: Default template for PDM package
Author-email: thephunkmonk <andrewchoi1218@gmail.com>
License: MIT
Requires-Python: >=3.9
Requires-Dist: wtf-plus >=0.1.0
Requires-Dist: wtf-div >=0.1.0
Requires-Dist: wtf-mul >=0.1.0
